{
  "geometry": {
    "coordinates": [
      [
        [
          -103.02964581185738,
          34.307820470335585
        ],
        [
          -103.7268131258707,
          34.30604929022733
        ],
        [
          -103.72901054961542,
          34.60144861507104
        ],
        [
          -103.69264805103958,
          34.601620656286
        ],
        [
          -103.6959670840421,
          34.68365722230983
        ],
        [
          -103.48200324295266,
          34.68511965034306
        ],
        [
          -103.48205680832943,
          34.78611442263825
        ],
        [
          -103.37928577913013,
          34.78850279607232
        ],
        [
          -103.3762875167398,
          34.875700857565185
        ],
        [
          -103.27392076626423,
          34.87847449764053
        ],
        [
          -103.26983897058508,
          34.963341791791166
        ],
        [
          -103.02525127519218,
          34.96477987192586
        ],
        [
          -103.02265703250538,
          34.74533278047847
        ],
        [
          -103.02964581185738,
          34.307820470335585
        ]
      ]
    ],
    "type": "Polygon"
  },
  "properties": {
    "FIPS": "35009",
    "CNTY_FIPS": "009",
    "STATE_FIPS": "35",
    "STATE_NAME": "New Mexico",
    "NAME": "Curry"
  },
  "type": "Feature"
}
