{
  "geometry": {
    "coordinates": [
      [
        [
          -97.25197242798397,
          41.38763863530693
        ],
        [
          -97.2472053684712,
          41.7405255243593
        ],
        [
          -97.01842598653589,
          41.745031595121404
        ],
        [
          -96.90274704843883,
          41.74322130296338
        ],
        [
          -96.90360647745304,
          41.45784611155423
        ],
        [
          -96.94639283233084,
          41.450740151465034
        ],
        [
          -97.00221805671809,
          41.421814848006534
        ],
        [
          -97.05176452791783,
          41.41400305788004
        ],
        [
          -97.10787255055635,
          41.38913613467486
        ],
        [
          -97.1686117507122,
          41.37803245686252
        ],
        [
          -97.25197242798397,
          41.38763863530693
        ]
      ]
    ],
    "type": "Polygon"
  },
  "properties": {
    "FIPS": "31037",
    "CNTY_FIPS": "037",
    "STATE_FIPS": "31",
    "STATE_NAME": "Nebraska",
    "NAME": "Colfax"
  },
  "type": "Feature"
}
