{
  "geometry": {
    "coordinates": [
      [
        [
          -95.18170630861313,
          39.0375420662797
        ],
        [
          -95.34821303902129,
          39.03410414300668
        ],
        [
          -95.38274410939101,
          39.053978400107354
        ],
        [
          -95.43335831364753,
          39.066455972849525
        ],
        [
          -95.49610357342644,
          39.0545197005154
        ],
        [
          -95.5404468469054,
          39.063926640624146
        ],
        [
          -95.5889788396009,
          39.05852513704042
        ],
        [
          -95.59919480339349,
          39.09352456773067
        ],
        [
          -95.58693387514424,
          39.141989681411246
        ],
        [
          -95.58632331273546,
          39.21507456122488
        ],
        [
          -95.58202855065021,
          39.413338825535504
        ],
        [
          -95.56531206057728,
          39.41345346787477
        ],
        [
          -95.16974138864519,
          39.41306866746985
        ],
        [
          -95.18170630861313,
          39.0375420662797
        ]
      ]
    ],
    "type": "Polygon"
  },
  "properties": {
    "FIPS": "20087",
    "CNTY_FIPS": "087",
    "STATE_FIPS": "20",
    "STATE_NAME": "Kansas",
    "NAME": "Jefferson"
  },
  "type": "Feature"
}
