{
  "geometry": {
    "coordinates": [
      [
        [
          -97.80012013855269,
          37.46626229750696
        ],
        [
          -97.80118657650847,
          37.724400168278535
        ],
        [
          -97.69506719322034,
          37.72703202069795
        ],
        [
          -97.697361749539,
          37.909007903517534
        ],
        [
          -97.14785894890677,
          37.91063973075971
        ],
        [
          -97.14275925565678,
          37.47304645090319
        ],
        [
          -97.80012013855269,
          37.46626229750696
        ]
      ]
    ],
    "type": "Polygon"
  },
  "properties": {
    "FIPS": "20173",
    "CNTY_FIPS": "173",
    "STATE_FIPS": "20",
    "STATE_NAME": "Kansas",
    "NAME": "Sedgwick"
  },
  "type": "Feature"
}
