{
  "geometry": {
    "coordinates": [
      [
        [
          -100.95058683746123,
          36.99666168466983
        ],
        [
          -101.071604181822,
          36.99746671944264
        ],
        [
          -101.06718555627845,
          37.38853214947726
        ],
        [
          -100.64667305250015,
          37.38720684673641
        ],
        [
          -100.6351141725933,
          37.38485696370364
        ],
        [
          -100.63424562606815,
          36.99783235235297
        ],
        [
          -100.95058683746123,
          36.99666168466983
        ]
      ]
    ],
    "type": "Polygon"
  },
  "properties": {
    "FIPS": "20175",
    "CNTY_FIPS": "175",
    "STATE_FIPS": "20",
    "STATE_NAME": "Kansas",
    "NAME": "Seward"
  },
  "type": "Feature"
}
