{
  "geometry": {
    "coordinates": [
      [
        [
          -87.1104714508521,
          46.16098985228275
        ],
        [
          -87.1106791332462,
          46.501473351977424
        ],
        [
          -87.00640195340438,
          46.536293644299306
        ],
        [
          -86.8713827024411,
          46.444359709325404
        ],
        [
          -86.75949571642255,
          46.486631494679514
        ],
        [
          -86.63822033614136,
          46.42226373238552
        ],
        [
          -86.46239203868144,
          46.56108555525539
        ],
        [
          -86.14810910538316,
          46.673053096555265
        ],
        [
          -86.0967390801913,
          46.65526856260133
        ],
        [
          -85.85753646650161,
          46.69481514465696
        ],
        [
          -85.85867625897724,
          46.50785503979129
        ],
        [
          -86.36188111611457,
          46.50699597340535
        ],
        [
          -86.36406273962727,
          46.336028086337265
        ],
        [
          -86.60972231240011,
          46.335026662450964
        ],
        [
          -86.6100303392186,
          46.16229365634724
        ],
        [
          -87.1104714508521,
          46.16098985228275
        ]
      ]
    ],
    "type": "Polygon"
  },
  "properties": {
    "FIPS": "26003",
    "CNTY_FIPS": "003",
    "STATE_FIPS": "26",
    "STATE_NAME": "Michigan",
    "NAME": "Alger"
  },
  "type": "Feature"
}
