{
  "geometry": {
    "coordinates": [
      [
        [
          -85.33626002922784,
          44.5131285864467
        ],
        [
          -85.33379685076082,
          44.81349534882772
        ],
        [
          -85.31920215053505,
          44.851413470903736
        ],
        [
          -85.29358137494802,
          44.85929493746326
        ],
        [
          -84.85196701374657,
          44.861152682121414
        ],
        [
          -84.85532070365147,
          44.51368977960588
        ],
        [
          -85.33626002922784,
          44.5131285864467
        ]
      ]
    ],
    "type": "Polygon"
  },
  "properties": {
    "FIPS": "26079",
    "CNTY_FIPS": "079",
    "STATE_FIPS": "26",
    "STATE_NAME": "Michigan",
    "NAME": "Kalkaska"
  },
  "type": "Feature"
}
