{
  "geometry": {
    "coordinates": [
      [
        [
          -83.56823696274229,
          44.17011803390439
        ],
        [
          -83.59840447526238,
          44.07049337484416
        ],
        [
          -83.7048019426342,
          43.99716522326135
        ],
        [
          -83.87361483346587,
          43.962842197913986
        ],
        [
          -83.9183762173471,
          43.91699764337223
        ],
        [
          -84.04591310007065,
          43.917013702624445
        ],
        [
          -84.0480520888589,
          44.00150857753559
        ],
        [
          -84.16646374184015,
          44.00176459309847
        ],
        [
          -84.1667772598868,
          44.16834364194569
        ],
        [
          -83.88383981116131,
          44.17036845463102
        ],
        [
          -83.56823696274229,
          44.17011803390439
        ]
      ]
    ],
    "type": "Polygon"
  },
  "properties": {
    "FIPS": "26011",
    "CNTY_FIPS": "011",
    "STATE_FIPS": "26",
    "STATE_NAME": "Michigan",
    "NAME": "Arenac"
  },
  "type": "Feature"
}
