{
  "geometry": {
    "coordinates": [
      [
        [
          -91.52985188285848,
          44.594084002167534
        ],
        [
          -91.65184029393843,
          44.59764677317558
        ],
        [
          -91.65384215743428,
          44.680652955405506
        ],
        [
          -91.65299868406422,
          44.85546402874709
        ],
        [
          -90.92353750892818,
          44.85743465440717
        ],
        [
          -90.92309945397072,
          44.59279972822592
        ],
        [
          -91.16426383482974,
          44.593661851050186
        ],
        [
          -91.52985188285848,
          44.594084002167534
        ]
      ]
    ],
    "type": "Polygon"
  },
  "properties": {
    "FIPS": "55035",
    "CNTY_FIPS": "035",
    "STATE_FIPS": "55",
    "STATE_NAME": "Wisconsin",
    "NAME": "Eau Claire"
  },
  "type": "Feature"
}
