{
  "geometry": {
    "coordinates": [
      [
        [
          -91.37742512774027,
          38.21080528625157
        ],
        [
          -91.54035023047003,
          38.213191898348306
        ],
        [
          -91.54290499847876,
          38.157385893259686
        ],
        [
          -91.63832021670669,
          38.15712236611108
        ],
        [
          -91.6523891059322,
          38.1577822459654
        ],
        [
          -91.65156801190716,
          38.28972242023683
        ],
        [
          -91.65373533750497,
          38.70358815493148
        ],
        [
          -91.65371249192359,
          38.70451508460907
        ],
        [
          -91.59416240168889,
          38.68285203402674
        ],
        [
          -91.56162169431828,
          38.678866024016514
        ],
        [
          -91.4939085307657,
          38.70400507384085
        ],
        [
          -91.42514970267715,
          38.71325623920301
        ],
        [
          -91.3752360444459,
          38.699062450438426
        ],
        [
          -91.36977698657435,
          38.41673178242682
        ],
        [
          -91.37742512774027,
          38.21080528625157
        ]
      ]
    ],
    "type": "Polygon"
  },
  "properties": {
    "FIPS": "29073",
    "CNTY_FIPS": "073",
    "STATE_FIPS": "29",
    "STATE_NAME": "Missouri",
    "NAME": "Gasconade"
  },
  "type": "Feature"
}
