{
  "geometry": {
    "coordinates": [
      [
        [
          -97.94296920744817,
          32.23998660242021
        ],
        [
          -98.06301641756244,
          32.519196646900326
        ],
        [
          -98.06043061893408,
          32.55833853579989
        ],
        [
          -97.61760461305431,
          32.55537285815036
        ],
        [
          -97.61422393324487,
          32.32332764596103
        ],
        [
          -97.78348746741557,
          32.3235812785381
        ],
        [
          -97.94296920744817,
          32.23998660242021
        ]
      ]
    ],
    "type": "Polygon"
  },
  "properties": {
    "FIPS": "48221",
    "CNTY_FIPS": "221",
    "STATE_FIPS": "48",
    "STATE_NAME": "Texas",
    "NAME": "Hood"
  },
  "type": "Feature"
}
