{
  "geometry": {
    "coordinates": [
      [
        [
          -103.5723162813367,
          40.99964844846525
        ],
        [
          -104.05170552644512,
          41.00321132308138
        ],
        [
          -104.05401236032112,
          41.388085807775326
        ],
        [
          -103.37563566651158,
          41.390728642651105
        ],
        [
          -103.37309193276324,
          41.04175477171741
        ],
        [
          -103.38295666516848,
          41.00031635794568
        ],
        [
          -103.5723162813367,
          40.99964844846525
        ]
      ]
    ],
    "type": "Polygon"
  },
  "properties": {
    "FIPS": "31105",
    "CNTY_FIPS": "105",
    "STATE_FIPS": "31",
    "STATE_NAME": "Nebraska",
    "NAME": "Kimball"
  },
  "type": "Feature"
}
