{
  "geometry": {
    "coordinates": [
      [
        [
          -99.00920574913617,
          46.28302778802441
        ],
        [
          -99.04408012487522,
          46.28338274930261
        ],
        [
          -99.03877021083322,
          46.63519009397721
        ],
        [
          -98.43976248584089,
          46.63191882429905
        ],
        [
          -98.0366477470581,
          46.629178856849336
        ],
        [
          -98.04288956396549,
          46.282292222468485
        ],
        [
          -99.00920574913617,
          46.28302778802441
        ]
      ]
    ],
    "type": "Polygon"
  },
  "properties": {
    "FIPS": "38045",
    "CNTY_FIPS": "045",
    "STATE_FIPS": "38",
    "STATE_NAME": "North Dakota",
    "NAME": "LaMoure"
  },
  "type": "Feature"
}
