{
  "geometry": {
    "coordinates": [
      [
        [
          -92.32047798374644,
          44.54049106564355
        ],
        [
          -92.13592350305998,
          44.541982348526744
        ],
        [
          -92.13488985706115,
          44.679802074057804
        ],
        [
          -91.65384215743428,
          44.680652955405506
        ],
        [
          -91.65184029393843,
          44.59764677317558
        ],
        [
          -92.016139405662,
          44.59584865496682
        ],
        [
          -92.03884444269352,
          44.568497779874804
        ],
        [
          -92.050165075823,
          44.51171687456807
        ],
        [
          -92.09133338333312,
          44.41558981703429
        ],
        [
          -92.20613745481221,
          44.43839442142959
        ],
        [
          -92.2491003578564,
          44.45621677233231
        ],
        [
          -92.29668749667667,
          44.492181882121656
        ],
        [
          -92.32047798374644,
          44.54049106564355
        ]
      ]
    ],
    "type": "Polygon"
  },
  "properties": {
    "FIPS": "55091",
    "CNTY_FIPS": "091",
    "STATE_FIPS": "55",
    "STATE_NAME": "Wisconsin",
    "NAME": "Pepin"
  },
  "type": "Feature"
}
