{
  "geometry": {
    "coordinates": [
      [
        [
          -93.04934755675215,
          44.19692077045515
        ],
        [
          -93.05201660447189,
          43.84581821973706
        ],
        [
          -93.41198764411284,
          43.84705509298259
        ],
        [
          -93.41045926953741,
          44.19681669613993
        ],
        [
          -93.04934755675215,
          44.19692077045515
        ]
      ]
    ],
    "type": "Polygon"
  },
  "properties": {
    "FIPS": "27147",
    "CNTY_FIPS": "147",
    "STATE_FIPS": "27",
    "STATE_NAME": "Minnesota",
    "NAME": "Steele"
  },
  "type": "Feature"
}
