{
  "geometry": {
    "coordinates": [
      [
        [
          -101.17358571746033,
          32.95258929261124
        ],
        [
          -101.56075973166071,
          32.956601360053305
        ],
        [
          -101.56277128251195,
          33.39031886889551
        ],
        [
          -101.04545666276199,
          33.39209631729254
        ],
        [
          -101.04186104799294,
          32.955232800939534
        ],
        [
          -101.17358571746033,
          32.95258929261124
        ]
      ]
    ],
    "type": "Polygon"
  },
  "properties": {
    "FIPS": "48169",
    "CNTY_FIPS": "169",
    "STATE_FIPS": "48",
    "STATE_NAME": "Texas",
    "NAME": "Garza"
  },
  "type": "Feature"
}
