{
  "geometry": {
    "coordinates": [
      [
        [
          -89.71668568852509,
          34.193896083250124
        ],
        [
          -89.71550305410885,
          34.16799463337744
        ],
        [
          -89.93037232619952,
          34.167851032580124
        ],
        [
          -89.96758119917163,
          34.169979919580676
        ],
        [
          -89.96642151394487,
          34.16180508674583
        ],
        [
          -90.13574166993065,
          34.16100072542554
        ],
        [
          -90.13385797144875,
          34.26962685437786
        ],
        [
          -90.19313137630881,
          34.30836824624856
        ],
        [
          -90.19780907385358,
          34.51915235539753
        ],
        [
          -90.19986932050188,
          34.56184162950544
        ],
        [
          -89.7154944546383,
          34.566009575302154
        ],
        [
          -89.71668568852509,
          34.193896083250124
        ]
      ]
    ],
    "type": "Polygon"
  },
  "properties": {
    "FIPS": "28107",
    "CNTY_FIPS": "107",
    "STATE_FIPS": "28",
    "STATE_NAME": "Mississippi",
    "NAME": "Panola"
  },
  "type": "Feature"
}
