{
  "geometry": {
    "coordinates": [
      [
        [
          -78.37035133177861,
          38.1841086961776
        ],
        [
          -78.65809717964034,
          38.27419265709927
        ],
        [
          -78.65534275886363,
          38.285098598893086
        ],
        [
          -78.60894597326148,
          38.319067802651105
        ],
        [
          -78.56099278709858,
          38.32946280120398
        ],
        [
          -78.48943970092698,
          38.41843903635042
        ],
        [
          -78.45430454365342,
          38.471748345758506
        ],
        [
          -78.43449856427672,
          38.440170986305205
        ],
        [
          -78.44053404569505,
          38.40658715279653
        ],
        [
          -78.4297231643136,
          38.38763231378775
        ],
        [
          -78.43476659837675,
          38.36900938325961
        ],
        [
          -78.37837681356775,
          38.316398444107136
        ],
        [
          -78.35779978286811,
          38.31291959564297
        ],
        [
          -78.36229383509308,
          38.29611623019592
        ],
        [
          -78.32386373369533,
          38.26782728755783
        ],
        [
          -78.28753905206828,
          38.26942191949969
        ],
        [
          -78.37035133177861,
          38.1841086961776
        ]
      ]
    ],
    "type": "Polygon"
  },
  "properties": {
    "FIPS": "51079",
    "CNTY_FIPS": "079",
    "STATE_FIPS": "51",
    "STATE_NAME": "Virginia",
    "NAME": "Greene"
  },
  "type": "Feature"
}
