{
  "geometry": {
    "coordinates": [
      [
        [
          -78.1325196601885,
          39.19174663242321
        ],
        [
          -78.13940897578479,
          39.164971921857784
        ],
        [
          -78.16230506611373,
          39.13856341404711
        ],
        [
          -78.20520611513484,
          39.15781581545841
        ],
        [
          -78.20476370863808,
          39.17323062543247
        ],
        [
          -78.18248558869554,
          39.20281668941395
        ],
        [
          -78.1325196601885,
          39.19174663242321
        ]
      ]
    ],
    "type": "Polygon"
  },
  "properties": {
    "FIPS": "51840",
    "CNTY_FIPS": "840",
    "STATE_FIPS": "51",
    "STATE_NAME": "Virginia",
    "NAME": "Winchester"
  },
  "type": "Feature"
}
